scrutinize/__init__.py
scrutinize/client.py
scrutinize/seed.py
scrutinize-0.0.6.dist-info/LICENSE
scrutinize-0.0.6.dist-info/METADATA
scrutinize-0.0.6.dist-info/WHEEL
scrutinize-0.0.6.dist-info/top_level.txt
scrutinize-0.0.6.dist-info/RECORD
