Metadata-Version: 2.1
Name: scrutinize
Version: 0.0.6
Summary: the lightweight experimentation platform
Home-page: http://github.com/angles-n-daemons/scrutinize
Author: brian dillmann
Author-email: dillmann.brian@gmail.com
License: MIT
Platform: UNKNOWN
Classifier: Programming Language :: Python :: 3
Classifier: License :: OSI Approved :: MIT License
Classifier: Operating System :: OS Independent
Requires-Dist: aiohttp
